ndtiff/__init__.py
ndtiff/_superclass.py
ndtiff/_version.py
ndtiff/file_io.py
ndtiff/ndram_dataset.py
ndtiff/ndstorage_base.py
ndtiff/ndtiff_dataset.py
ndtiff/ndtiff_file.py
ndtiff/ndtiff_index.py
ndtiff/ndtiff_pyramid_dataset.py
ndtiff/old_format_version_readers/__init__.py
ndtiff/old_format_version_readers/nd_tiff_v2.py
ndtiff/old_format_version_readers/ndtiff_v1.py
ndtiff/test/__init__.py
ndtiff/test/conftest.py
ndtiff/test/data_loading_test.py
ndtiff/test/test_custom_io.py
ndtiff/test/write_speed_test.py
ndtiff/test/writing_test.py
ndtiff-3.1.0.dist-info/METADATA
ndtiff-3.1.0.dist-info/WHEEL
ndtiff-3.1.0.dist-info/top_level.txt
ndtiff-3.1.0.dist-info/RECORD
